odoo8_addon_sale_product_set_layout-8.0.1.0.0.99.dev6-py2.7-nspkg.pth
odoo8_addon_sale_product_set_layout-8.0.1.0.0.99.dev6.dist-info/DESCRIPTION.rst
odoo8_addon_sale_product_set_layout-8.0.1.0.0.99.dev6.dist-info/METADATA
odoo8_addon_sale_product_set_layout-8.0.1.0.0.99.dev6.dist-info/RECORD
odoo8_addon_sale_product_set_layout-8.0.1.0.0.99.dev6.dist-info/WHEEL
odoo8_addon_sale_product_set_layout-8.0.1.0.0.99.dev6.dist-info/metadata.json
odoo8_addon_sale_product_set_layout-8.0.1.0.0.99.dev6.dist-info/namespace_packages.txt
odoo8_addon_sale_product_set_layout-8.0.1.0.0.99.dev6.dist-info/top_level.txt
odoo_addons/sale_product_set_layout/README.rst
odoo_addons/sale_product_set_layout/__init__.py
odoo_addons/sale_product_set_layout/__openerp__.py
odoo_addons/sale_product_set_layout/demo/product_set.xml
odoo_addons/sale_product_set_layout/i18n/de.po
odoo_addons/sale_product_set_layout/i18n/es.po
odoo_addons/sale_product_set_layout/i18n/fr.po
odoo_addons/sale_product_set_layout/i18n/sale_product_set_layout.pot
odoo_addons/sale_product_set_layout/i18n/sl.po
odoo_addons/sale_product_set_layout/i18n/tr_TR.po
odoo_addons/sale_product_set_layout/models/__init__.py
odoo_addons/sale_product_set_layout/models/product_set.py
odoo_addons/sale_product_set_layout/static/description/icon.png
odoo_addons/sale_product_set_layout/static/description/icon.svg
odoo_addons/sale_product_set_layout/tests/__init__.py
odoo_addons/sale_product_set_layout/tests/test_product_set_layout.py
odoo_addons/sale_product_set_layout/views/product_set.xml
odoo_addons/sale_product_set_layout/wizard/__init__.py
odoo_addons/sale_product_set_layout/wizard/product_set_add.py
