Metadata-Version: 2.0
Name: odoo8-addon-sale-product-set-layout
Version: 8.0.1.0.0.99.dev6
Summary: Sale product set layout
Home-page: http://anybox.fr
Author: Anybox, Odoo Community Association (OCA)
Author-email: support@odoo-community.org
License: UNKNOWN
Platform: UNKNOWN
Classifier: Programming Language :: Python
Classifier: Framework :: Odoo
Requires-Python: ~=2.7
Requires-Dist: odoo (<9.0a,>=8.0a)
Requires-Dist: odoo8-addon-sale-product-set
